rtl/half_adder.v
module half_adder (
input a,
input b,
output sum,
output carry
);

xor (sum,a,b);
and (carry,a,b);

endmodule

rtl/full_adder.v
module full_adder (
input a,
input b,
input cin,
output sum,
output cout
);

wire s1;
wire c1;
wire c2;

half_adder a1 (
.a(a),
.b(b),
.carry(c1),
.sum(s1)
);

half_adder a2 (
.a(cin),
.b(s1),
.sum(sum),
.carry(c2)
);

or (cout,c1,c2);

endmodule

tb/tb_full_adder.v
module tb_full_adder ;

reg a;
reg b;
reg cin;
wire sum;
wire cout;

integer i;

full_adder dut (
.a(a),
.b(b),
.cin(cin),
.sum(sum),
.cout(cout)
);

initial begin 
$dumpfile("wave.vcd");
$dumpvars(1,tb_full_adder);

for (i = 0; i < 8; i = i + 1) begin
{cin, a, b } = i;
#10;
end

$finish;

end

endmodule

wave.vcd
$date
	Sat Jul 18 17:52:36 2026
$end
$version
	Icarus Verilog
$end
$timescale
	1s
$end
$scope module tb_full_adder $end
$var wire 1 ! sum $end
$var wire 1 " cout $end
$var reg 1 # a $end
$var reg 1 $ b $end
$var reg 1 % cin $end
$var integer 32 & i [31:0] $end
$upscope $end
$enddefinitions $end
$comment Show the parameter values. $end
$dumpall
$end
#0
$dumpvars
b0 &
0%
0$
0#
0"
0!
$end
#10
1!
1$
b1 &
#20
1#
0$
b10 &
#30
0!
1"
1$
b11 &
#40
0"
1!
1%
0#
0$
b100 &
#50
1"
0!
1$
b101 &
#60
1#
0$
b110 &
#70
1!
1$
b111 &
#80
b1000 &
